ormspace/__init__.py
ormspace/alias.py
ormspace/annotations.py
ormspace/bases.py
ormspace/containers.py
ormspace/context.py
ormspace/database.py
ormspace/enum.py
ormspace/exception.py
ormspace/functions.py
ormspace/keys.py
ormspace/metainfo.py
ormspace/model.py
ormspace/settings.py
ormspace-0.3.1.dist-info/WHEEL
ormspace-0.3.1.dist-info/METADATA
ormspace-0.3.1.dist-info/RECORD
